{
  "id": "579d6790-e3a8-4281-b680-7123f4d400a1",
  "prevId": "00000000-0000-0000-0000-000000000000",
  "version": "7",
  "dialect": "postgresql",
  "tables": {
    "public.users": {
      "name": "users",
      "schema": "",
      "columns": {
        "id": {
          "name": "id",
          "type": "serial",
          "primaryKey": true,
          "notNull": true
        },
        "updated_at": {
          "name": "updated_at",
          "type": "timestamp(3) with time zone",
          "primaryKey": false,
          "notNull": true,
          "default": "now()"
        },
        "created_at": {
          "name": "created_at",
          "type": "timestamp(3) with time zone",
          "primaryKey": false,
          "notNull": true,
          "default": "now()"
        },
        "email": {
          "name": "email",
          "type": "varchar",
          "primaryKey": false,
          "notNull": true
        },
        "reset_password_token": {
          "name": "reset_password_token",
          "type": "varchar",
          "primaryKey": false,
          "notNull": false
        },
        "reset_password_expiration": {
          "name": "reset_password_expiration",
          "type": "timestamp(3) with time zone",
          "primaryKey": false,
          "notNull": false
        },
        "salt": {
          "name": "salt",
          "type": "varchar",
          "primaryKey": false,
          "notNull": false
        },
        "hash": {
          "name": "hash",
          "type": "varchar",
          "primaryKey": false,
          "notNull": false
        },
        "login_attempts": {
          "name": "login_attempts",
          "type": "numeric",
          "primaryKey": false,
          "notNull": false,
          "default": 0
        },
        "lock_until": {
          "name": "lock_until",
          "type": "timestamp(3) with time zone",
          "primaryKey": false,
          "notNull": false
        }
      },
      "indexes": {
        "users_updated_at_idx": {
          "name": "users_updated_at_idx",
          "columns": [
            {
              "expression": "updated_at",
              "isExpression": false,
              "asc": true,
              "nulls": "last"
            }
          ],
          "isUnique": false,
          "concurrently": false,
          "method": "btree",
          "with": {}
        },
        "users_created_at_idx": {
          "name": "users_created_at_idx",
          "columns": [
            {
              "expression": "created_at",
              "isExpression": false,
              "asc": true,
              "nulls": "last"
            }
          ],
          "isUnique": false,
          "concurrently": false,
          "method": "btree",
          "with": {}
        },
        "users_email_idx": {
          "name": "users_email_idx",
          "columns": [
            {
              "expression": "email",
              "isExpression": false,
              "asc": true,
              "nulls": "last"
            }
          ],
          "isUnique": true,
          "concurrently": false,
          "method": "btree",
          "with": {}
        }
      },
      "foreignKeys": {},
      "compositePrimaryKeys": {},
      "uniqueConstraints": {},
      "policies": {},
      "checkConstraints": {},
      "isRLSEnabled": false
    },
    "public.media": {
      "name": "media",
      "schema": "",
      "columns": {
        "id": {
          "name": "id",
          "type": "serial",
          "primaryKey": true,
          "notNull": true
        },
        "alt": {
          "name": "alt",
          "type": "varchar",
          "primaryKey": false,
          "notNull": true
        },
        "updated_at": {
          "name": "updated_at",
          "type": "timestamp(3) with time zone",
          "primaryKey": false,
          "notNull": true,
          "default": "now()"
        },
        "created_at": {
          "name": "created_at",
          "type": "timestamp(3) with time zone",
          "primaryKey": false,
          "notNull": true,
          "default": "now()"
        },
        "url": {
          "name": "url",
          "type": "varchar",
          "primaryKey": false,
          "notNull": false
        },
        "thumbnail_u_r_l": {
          "name": "thumbnail_u_r_l",
          "type": "varchar",
          "primaryKey": false,
          "notNull": false
        },
        "filename": {
          "name": "filename",
          "type": "varchar",
          "primaryKey": false,
          "notNull": false
        },
        "mime_type": {
          "name": "mime_type",
          "type": "varchar",
          "primaryKey": false,
          "notNull": false
        },
        "filesize": {
          "name": "filesize",
          "type": "numeric",
          "primaryKey": false,
          "notNull": false
        },
        "width": {
          "name": "width",
          "type": "numeric",
          "primaryKey": false,
          "notNull": false
        },
        "height": {
          "name": "height",
          "type": "numeric",
          "primaryKey": false,
          "notNull": false
        },
        "focal_x": {
          "name": "focal_x",
          "type": "numeric",
          "primaryKey": false,
          "notNull": false
        },
        "focal_y": {
          "name": "focal_y",
          "type": "numeric",
          "primaryKey": false,
          "notNull": false
        }
      },
      "indexes": {
        "media_updated_at_idx": {
          "name": "media_updated_at_idx",
          "columns": [
            {
              "expression": "updated_at",
              "isExpression": false,
              "asc": true,
              "nulls": "last"
            }
          ],
          "isUnique": false,
          "concurrently": false,
          "method": "btree",
          "with": {}
        },
        "media_created_at_idx": {
          "name": "media_created_at_idx",
          "columns": [
            {
              "expression": "created_at",
              "isExpression": false,
              "asc": true,
              "nulls": "last"
            }
          ],
          "isUnique": false,
          "concurrently": false,
          "method": "btree",
          "with": {}
        },
        "media_filename_idx": {
          "name": "media_filename_idx",
          "columns": [
            {
              "expression": "filename",
              "isExpression": false,
              "asc": true,
              "nulls": "last"
            }
          ],
          "isUnique": true,
          "concurrently": false,
          "method": "btree",
          "with": {}
        }
      },
      "foreignKeys": {},
      "compositePrimaryKeys": {},
      "uniqueConstraints": {},
      "policies": {},
      "checkConstraints": {},
      "isRLSEnabled": false
    },
    "public.pages_blocks_content": {
      "name": "pages_blocks_content",
      "schema": "",
      "columns": {
        "_order": {
          "name": "_order",
          "type": "integer",
          "primaryKey": false,
          "notNull": true
        },
        "_parent_id": {
          "name": "_parent_id",
          "type": "integer",
          "primaryKey": false,
          "notNull": true
        },
        "_path": {
          "name": "_path",
          "type": "text",
          "primaryKey": false,
          "notNull": true
        },
        "id": {
          "name": "id",
          "type": "varchar",
          "primaryKey": true,
          "notNull": true
        },
        "title": {
          "name": "title",
          "type": "varchar",
          "primaryKey": false,
          "notNull": false
        },
        "content": {
          "name": "content",
          "type": "jsonb",
          "primaryKey": false,
          "notNull": false
        },
        "background_image_id": {
          "name": "background_image_id",
          "type": "integer",
          "primaryKey": false,
          "notNull": false
        },
        "block_name": {
          "name": "block_name",
          "type": "varchar",
          "primaryKey": false,
          "notNull": false
        }
      },
      "indexes": {
        "pages_blocks_content_order_idx": {
          "name": "pages_blocks_content_order_idx",
          "columns": [
            {
              "expression": "_order",
              "isExpression": false,
              "asc": true,
              "nulls": "last"
            }
          ],
          "isUnique": false,
          "concurrently": false,
          "method": "btree",
          "with": {}
        },
        "pages_blocks_content_parent_id_idx": {
          "name": "pages_blocks_content_parent_id_idx",
          "columns": [
            {
              "expression": "_parent_id",
              "isExpression": false,
              "asc": true,
              "nulls": "last"
            }
          ],
          "isUnique": false,
          "concurrently": false,
          "method": "btree",
          "with": {}
        },
        "pages_blocks_content_path_idx": {
          "name": "pages_blocks_content_path_idx",
          "columns": [
            {
              "expression": "_path",
              "isExpression": false,
              "asc": true,
              "nulls": "last"
            }
          ],
          "isUnique": false,
          "concurrently": false,
          "method": "btree",
          "with": {}
        },
        "pages_blocks_content_background_image_idx": {
          "name": "pages_blocks_content_background_image_idx",
          "columns": [
            {
              "expression": "background_image_id",
              "isExpression": false,
              "asc": true,
              "nulls": "last"
            }
          ],
          "isUnique": false,
          "concurrently": false,
          "method": "btree",
          "with": {}
        }
      },
      "foreignKeys": {
        "pages_blocks_content_background_image_id_media_id_fk": {
          "name": "pages_blocks_content_background_image_id_media_id_fk",
          "tableFrom": "pages_blocks_content",
          "tableTo": "media",
          "columnsFrom": [
            "background_image_id"
          ],
          "columnsTo": [
            "id"
          ],
          "onDelete": "set null",
          "onUpdate": "no action"
        },
        "pages_blocks_content_parent_id_fk": {
          "name": "pages_blocks_content_parent_id_fk",
          "tableFrom": "pages_blocks_content",
          "tableTo": "pages",
          "columnsFrom": [
            "_parent_id"
          ],
          "columnsTo": [
            "id"
          ],
          "onDelete": "cascade",
          "onUpdate": "no action"
        }
      },
      "compositePrimaryKeys": {},
      "uniqueConstraints": {},
      "policies": {},
      "checkConstraints": {},
      "isRLSEnabled": false
    },
    "public.pages_blocks_hero_ctas": {
      "name": "pages_blocks_hero_ctas",
      "schema": "",
      "columns": {
        "_order": {
          "name": "_order",
          "type": "integer",
          "primaryKey": false,
          "notNull": true
        },
        "_parent_id": {
          "name": "_parent_id",
          "type": "varchar",
          "primaryKey": false,
          "notNull": true
        },
        "id": {
          "name": "id",
          "type": "varchar",
          "primaryKey": true,
          "notNull": true
        },
        "label": {
          "name": "label",
          "type": "varchar",
          "primaryKey": false,
          "notNull": true
        },
        "url": {
          "name": "url",
          "type": "varchar",
          "primaryKey": false,
          "notNull": true
        },
        "icon": {
          "name": "icon",
          "type": "enum_pages_blocks_hero_ctas_icon",
          "typeSchema": "public",
          "primaryKey": false,
          "notNull": false
        }
      },
      "indexes": {
        "pages_blocks_hero_ctas_order_idx": {
          "name": "pages_blocks_hero_ctas_order_idx",
          "columns": [
            {
              "expression": "_order",
              "isExpression": false,
              "asc": true,
              "nulls": "last"
            }
          ],
          "isUnique": false,
          "concurrently": false,
          "method": "btree",
          "with": {}
        },
        "pages_blocks_hero_ctas_parent_id_idx": {
          "name": "pages_blocks_hero_ctas_parent_id_idx",
          "columns": [
            {
              "expression": "_parent_id",
              "isExpression": false,
              "asc": true,
              "nulls": "last"
            }
          ],
          "isUnique": false,
          "concurrently": false,
          "method": "btree",
          "with": {}
        }
      },
      "foreignKeys": {
        "pages_blocks_hero_ctas_parent_id_fk": {
          "name": "pages_blocks_hero_ctas_parent_id_fk",
          "tableFrom": "pages_blocks_hero_ctas",
          "tableTo": "pages_blocks_hero",
          "columnsFrom": [
            "_parent_id"
          ],
          "columnsTo": [
            "id"
          ],
          "onDelete": "cascade",
          "onUpdate": "no action"
        }
      },
      "compositePrimaryKeys": {},
      "uniqueConstraints": {},
      "policies": {},
      "checkConstraints": {},
      "isRLSEnabled": false
    },
    "public.pages_blocks_hero": {
      "name": "pages_blocks_hero",
      "schema": "",
      "columns": {
        "_order": {
          "name": "_order",
          "type": "integer",
          "primaryKey": false,
          "notNull": true
        },
        "_parent_id": {
          "name": "_parent_id",
          "type": "integer",
          "primaryKey": false,
          "notNull": true
        },
        "_path": {
          "name": "_path",
          "type": "text",
          "primaryKey": false,
          "notNull": true
        },
        "id": {
          "name": "id",
          "type": "varchar",
          "primaryKey": true,
          "notNull": true
        },
        "title": {
          "name": "title",
          "type": "varchar",
          "primaryKey": false,
          "notNull": false
        },
        "content": {
          "name": "content",
          "type": "jsonb",
          "primaryKey": false,
          "notNull": false
        },
        "image_id": {
          "name": "image_id",
          "type": "integer",
          "primaryKey": false,
          "notNull": true
        },
        "image_position": {
          "name": "image_position",
          "type": "enum_pages_blocks_hero_image_position",
          "typeSchema": "public",
          "primaryKey": false,
          "notNull": false,
          "default": "'right'"
        },
        "block_name": {
          "name": "block_name",
          "type": "varchar",
          "primaryKey": false,
          "notNull": false
        }
      },
      "indexes": {
        "pages_blocks_hero_order_idx": {
          "name": "pages_blocks_hero_order_idx",
          "columns": [
            {
              "expression": "_order",
              "isExpression": false,
              "asc": true,
              "nulls": "last"
            }
          ],
          "isUnique": false,
          "concurrently": false,
          "method": "btree",
          "with": {}
        },
        "pages_blocks_hero_parent_id_idx": {
          "name": "pages_blocks_hero_parent_id_idx",
          "columns": [
            {
              "expression": "_parent_id",
              "isExpression": false,
              "asc": true,
              "nulls": "last"
            }
          ],
          "isUnique": false,
          "concurrently": false,
          "method": "btree",
          "with": {}
        },
        "pages_blocks_hero_path_idx": {
          "name": "pages_blocks_hero_path_idx",
          "columns": [
            {
              "expression": "_path",
              "isExpression": false,
              "asc": true,
              "nulls": "last"
            }
          ],
          "isUnique": false,
          "concurrently": false,
          "method": "btree",
          "with": {}
        },
        "pages_blocks_hero_image_idx": {
          "name": "pages_blocks_hero_image_idx",
          "columns": [
            {
              "expression": "image_id",
              "isExpression": false,
              "asc": true,
              "nulls": "last"
            }
          ],
          "isUnique": false,
          "concurrently": false,
          "method": "btree",
          "with": {}
        }
      },
      "foreignKeys": {
        "pages_blocks_hero_image_id_media_id_fk": {
          "name": "pages_blocks_hero_image_id_media_id_fk",
          "tableFrom": "pages_blocks_hero",
          "tableTo": "media",
          "columnsFrom": [
            "image_id"
          ],
          "columnsTo": [
            "id"
          ],
          "onDelete": "set null",
          "onUpdate": "no action"
        },
        "pages_blocks_hero_parent_id_fk": {
          "name": "pages_blocks_hero_parent_id_fk",
          "tableFrom": "pages_blocks_hero",
          "tableTo": "pages",
          "columnsFrom": [
            "_parent_id"
          ],
          "columnsTo": [
            "id"
          ],
          "onDelete": "cascade",
          "onUpdate": "no action"
        }
      },
      "compositePrimaryKeys": {},
      "uniqueConstraints": {},
      "policies": {},
      "checkConstraints": {},
      "isRLSEnabled": false
    },
    "public.pages_blocks_contact": {
      "name": "pages_blocks_contact",
      "schema": "",
      "columns": {
        "_order": {
          "name": "_order",
          "type": "integer",
          "primaryKey": false,
          "notNull": true
        },
        "_parent_id": {
          "name": "_parent_id",
          "type": "integer",
          "primaryKey": false,
          "notNull": true
        },
        "_path": {
          "name": "_path",
          "type": "text",
          "primaryKey": false,
          "notNull": true
        },
        "id": {
          "name": "id",
          "type": "varchar",
          "primaryKey": true,
          "notNull": true
        },
        "image_id": {
          "name": "image_id",
          "type": "integer",
          "primaryKey": false,
          "notNull": false
        },
        "block_name": {
          "name": "block_name",
          "type": "varchar",
          "primaryKey": false,
          "notNull": false
        }
      },
      "indexes": {
        "pages_blocks_contact_order_idx": {
          "name": "pages_blocks_contact_order_idx",
          "columns": [
            {
              "expression": "_order",
              "isExpression": false,
              "asc": true,
              "nulls": "last"
            }
          ],
          "isUnique": false,
          "concurrently": false,
          "method": "btree",
          "with": {}
        },
        "pages_blocks_contact_parent_id_idx": {
          "name": "pages_blocks_contact_parent_id_idx",
          "columns": [
            {
              "expression": "_parent_id",
              "isExpression": false,
              "asc": true,
              "nulls": "last"
            }
          ],
          "isUnique": false,
          "concurrently": false,
          "method": "btree",
          "with": {}
        },
        "pages_blocks_contact_path_idx": {
          "name": "pages_blocks_contact_path_idx",
          "columns": [
            {
              "expression": "_path",
              "isExpression": false,
              "asc": true,
              "nulls": "last"
            }
          ],
          "isUnique": false,
          "concurrently": false,
          "method": "btree",
          "with": {}
        },
        "pages_blocks_contact_image_idx": {
          "name": "pages_blocks_contact_image_idx",
          "columns": [
            {
              "expression": "image_id",
              "isExpression": false,
              "asc": true,
              "nulls": "last"
            }
          ],
          "isUnique": false,
          "concurrently": false,
          "method": "btree",
          "with": {}
        }
      },
      "foreignKeys": {
        "pages_blocks_contact_image_id_media_id_fk": {
          "name": "pages_blocks_contact_image_id_media_id_fk",
          "tableFrom": "pages_blocks_contact",
          "tableTo": "media",
          "columnsFrom": [
            "image_id"
          ],
          "columnsTo": [
            "id"
          ],
          "onDelete": "set null",
          "onUpdate": "no action"
        },
        "pages_blocks_contact_parent_id_fk": {
          "name": "pages_blocks_contact_parent_id_fk",
          "tableFrom": "pages_blocks_contact",
          "tableTo": "pages",
          "columnsFrom": [
            "_parent_id"
          ],
          "columnsTo": [
            "id"
          ],
          "onDelete": "cascade",
          "onUpdate": "no action"
        }
      },
      "compositePrimaryKeys": {},
      "uniqueConstraints": {},
      "policies": {},
      "checkConstraints": {},
      "isRLSEnabled": false
    },
    "public.pages_blocks_events": {
      "name": "pages_blocks_events",
      "schema": "",
      "columns": {
        "_order": {
          "name": "_order",
          "type": "integer",
          "primaryKey": false,
          "notNull": true
        },
        "_parent_id": {
          "name": "_parent_id",
          "type": "integer",
          "primaryKey": false,
          "notNull": true
        },
        "_path": {
          "name": "_path",
          "type": "text",
          "primaryKey": false,
          "notNull": true
        },
        "id": {
          "name": "id",
          "type": "varchar",
          "primaryKey": true,
          "notNull": true
        },
        "title": {
          "name": "title",
          "type": "varchar",
          "primaryKey": false,
          "notNull": false
        },
        "block_name": {
          "name": "block_name",
          "type": "varchar",
          "primaryKey": false,
          "notNull": false
        }
      },
      "indexes": {
        "pages_blocks_events_order_idx": {
          "name": "pages_blocks_events_order_idx",
          "columns": [
            {
              "expression": "_order",
              "isExpression": false,
              "asc": true,
              "nulls": "last"
            }
          ],
          "isUnique": false,
          "concurrently": false,
          "method": "btree",
          "with": {}
        },
        "pages_blocks_events_parent_id_idx": {
          "name": "pages_blocks_events_parent_id_idx",
          "columns": [
            {
              "expression": "_parent_id",
              "isExpression": false,
              "asc": true,
              "nulls": "last"
            }
          ],
          "isUnique": false,
          "concurrently": false,
          "method": "btree",
          "with": {}
        },
        "pages_blocks_events_path_idx": {
          "name": "pages_blocks_events_path_idx",
          "columns": [
            {
              "expression": "_path",
              "isExpression": false,
              "asc": true,
              "nulls": "last"
            }
          ],
          "isUnique": false,
          "concurrently": false,
          "method": "btree",
          "with": {}
        }
      },
      "foreignKeys": {
        "pages_blocks_events_parent_id_fk": {
          "name": "pages_blocks_events_parent_id_fk",
          "tableFrom": "pages_blocks_events",
          "tableTo": "pages",
          "columnsFrom": [
            "_parent_id"
          ],
          "columnsTo": [
            "id"
          ],
          "onDelete": "cascade",
          "onUpdate": "no action"
        }
      },
      "compositePrimaryKeys": {},
      "uniqueConstraints": {},
      "policies": {},
      "checkConstraints": {},
      "isRLSEnabled": false
    },
    "public.pages_blocks_image": {
      "name": "pages_blocks_image",
      "schema": "",
      "columns": {
        "_order": {
          "name": "_order",
          "type": "integer",
          "primaryKey": false,
          "notNull": true
        },
        "_parent_id": {
          "name": "_parent_id",
          "type": "integer",
          "primaryKey": false,
          "notNull": true
        },
        "_path": {
          "name": "_path",
          "type": "text",
          "primaryKey": false,
          "notNull": true
        },
        "id": {
          "name": "id",
          "type": "varchar",
          "primaryKey": true,
          "notNull": true
        },
        "image_id": {
          "name": "image_id",
          "type": "integer",
          "primaryKey": false,
          "notNull": true
        },
        "block_name": {
          "name": "block_name",
          "type": "varchar",
          "primaryKey": false,
          "notNull": false
        }
      },
      "indexes": {
        "pages_blocks_image_order_idx": {
          "name": "pages_blocks_image_order_idx",
          "columns": [
            {
              "expression": "_order",
              "isExpression": false,
              "asc": true,
              "nulls": "last"
            }
          ],
          "isUnique": false,
          "concurrently": false,
          "method": "btree",
          "with": {}
        },
        "pages_blocks_image_parent_id_idx": {
          "name": "pages_blocks_image_parent_id_idx",
          "columns": [
            {
              "expression": "_parent_id",
              "isExpression": false,
              "asc": true,
              "nulls": "last"
            }
          ],
          "isUnique": false,
          "concurrently": false,
          "method": "btree",
          "with": {}
        },
        "pages_blocks_image_path_idx": {
          "name": "pages_blocks_image_path_idx",
          "columns": [
            {
              "expression": "_path",
              "isExpression": false,
              "asc": true,
              "nulls": "last"
            }
          ],
          "isUnique": false,
          "concurrently": false,
          "method": "btree",
          "with": {}
        },
        "pages_blocks_image_image_idx": {
          "name": "pages_blocks_image_image_idx",
          "columns": [
            {
              "expression": "image_id",
              "isExpression": false,
              "asc": true,
              "nulls": "last"
            }
          ],
          "isUnique": false,
          "concurrently": false,
          "method": "btree",
          "with": {}
        }
      },
      "foreignKeys": {
        "pages_blocks_image_image_id_media_id_fk": {
          "name": "pages_blocks_image_image_id_media_id_fk",
          "tableFrom": "pages_blocks_image",
          "tableTo": "media",
          "columnsFrom": [
            "image_id"
          ],
          "columnsTo": [
            "id"
          ],
          "onDelete": "set null",
          "onUpdate": "no action"
        },
        "pages_blocks_image_parent_id_fk": {
          "name": "pages_blocks_image_parent_id_fk",
          "tableFrom": "pages_blocks_image",
          "tableTo": "pages",
          "columnsFrom": [
            "_parent_id"
          ],
          "columnsTo": [
            "id"
          ],
          "onDelete": "cascade",
          "onUpdate": "no action"
        }
      },
      "compositePrimaryKeys": {},
      "uniqueConstraints": {},
      "policies": {},
      "checkConstraints": {},
      "isRLSEnabled": false
    },
    "public.pages_blocks_image_slider_images": {
      "name": "pages_blocks_image_slider_images",
      "schema": "",
      "columns": {
        "_order": {
          "name": "_order",
          "type": "integer",
          "primaryKey": false,
          "notNull": true
        },
        "_parent_id": {
          "name": "_parent_id",
          "type": "varchar",
          "primaryKey": false,
          "notNull": true
        },
        "id": {
          "name": "id",
          "type": "varchar",
          "primaryKey": true,
          "notNull": true
        },
        "image_id": {
          "name": "image_id",
          "type": "integer",
          "primaryKey": false,
          "notNull": true
        },
        "caption": {
          "name": "caption",
          "type": "varchar",
          "primaryKey": false,
          "notNull": false
        }
      },
      "indexes": {
        "pages_blocks_image_slider_images_order_idx": {
          "name": "pages_blocks_image_slider_images_order_idx",
          "columns": [
            {
              "expression": "_order",
              "isExpression": false,
              "asc": true,
              "nulls": "last"
            }
          ],
          "isUnique": false,
          "concurrently": false,
          "method": "btree",
          "with": {}
        },
        "pages_blocks_image_slider_images_parent_id_idx": {
          "name": "pages_blocks_image_slider_images_parent_id_idx",
          "columns": [
            {
              "expression": "_parent_id",
              "isExpression": false,
              "asc": true,
              "nulls": "last"
            }
          ],
          "isUnique": false,
          "concurrently": false,
          "method": "btree",
          "with": {}
        },
        "pages_blocks_image_slider_images_image_idx": {
          "name": "pages_blocks_image_slider_images_image_idx",
          "columns": [
            {
              "expression": "image_id",
              "isExpression": false,
              "asc": true,
              "nulls": "last"
            }
          ],
          "isUnique": false,
          "concurrently": false,
          "method": "btree",
          "with": {}
        }
      },
      "foreignKeys": {
        "pages_blocks_image_slider_images_image_id_media_id_fk": {
          "name": "pages_blocks_image_slider_images_image_id_media_id_fk",
          "tableFrom": "pages_blocks_image_slider_images",
          "tableTo": "media",
          "columnsFrom": [
            "image_id"
          ],
          "columnsTo": [
            "id"
          ],
          "onDelete": "set null",
          "onUpdate": "no action"
        },
        "pages_blocks_image_slider_images_parent_id_fk": {
          "name": "pages_blocks_image_slider_images_parent_id_fk",
          "tableFrom": "pages_blocks_image_slider_images",
          "tableTo": "pages_blocks_image_slider",
          "columnsFrom": [
            "_parent_id"
          ],
          "columnsTo": [
            "id"
          ],
          "onDelete": "cascade",
          "onUpdate": "no action"
        }
      },
      "compositePrimaryKeys": {},
      "uniqueConstraints": {},
      "policies": {},
      "checkConstraints": {},
      "isRLSEnabled": false
    },
    "public.pages_blocks_image_slider": {
      "name": "pages_blocks_image_slider",
      "schema": "",
      "columns": {
        "_order": {
          "name": "_order",
          "type": "integer",
          "primaryKey": false,
          "notNull": true
        },
        "_parent_id": {
          "name": "_parent_id",
          "type": "integer",
          "primaryKey": false,
          "notNull": true
        },
        "_path": {
          "name": "_path",
          "type": "text",
          "primaryKey": false,
          "notNull": true
        },
        "id": {
          "name": "id",
          "type": "varchar",
          "primaryKey": true,
          "notNull": true
        },
        "title": {
          "name": "title",
          "type": "varchar",
          "primaryKey": false,
          "notNull": false
        },
        "block_name": {
          "name": "block_name",
          "type": "varchar",
          "primaryKey": false,
          "notNull": false
        }
      },
      "indexes": {
        "pages_blocks_image_slider_order_idx": {
          "name": "pages_blocks_image_slider_order_idx",
          "columns": [
            {
              "expression": "_order",
              "isExpression": false,
              "asc": true,
              "nulls": "last"
            }
          ],
          "isUnique": false,
          "concurrently": false,
          "method": "btree",
          "with": {}
        },
        "pages_blocks_image_slider_parent_id_idx": {
          "name": "pages_blocks_image_slider_parent_id_idx",
          "columns": [
            {
              "expression": "_parent_id",
              "isExpression": false,
              "asc": true,
              "nulls": "last"
            }
          ],
          "isUnique": false,
          "concurrently": false,
          "method": "btree",
          "with": {}
        },
        "pages_blocks_image_slider_path_idx": {
          "name": "pages_blocks_image_slider_path_idx",
          "columns": [
            {
              "expression": "_path",
              "isExpression": false,
              "asc": true,
              "nulls": "last"
            }
          ],
          "isUnique": false,
          "concurrently": false,
          "method": "btree",
          "with": {}
        }
      },
      "foreignKeys": {
        "pages_blocks_image_slider_parent_id_fk": {
          "name": "pages_blocks_image_slider_parent_id_fk",
          "tableFrom": "pages_blocks_image_slider",
          "tableTo": "pages",
          "columnsFrom": [
            "_parent_id"
          ],
          "columnsTo": [
            "id"
          ],
          "onDelete": "cascade",
          "onUpdate": "no action"
        }
      },
      "compositePrimaryKeys": {},
      "uniqueConstraints": {},
      "policies": {},
      "checkConstraints": {},
      "isRLSEnabled": false
    },
    "public.pages_blocks_header": {
      "name": "pages_blocks_header",
      "schema": "",
      "columns": {
        "_order": {
          "name": "_order",
          "type": "integer",
          "primaryKey": false,
          "notNull": true
        },
        "_parent_id": {
          "name": "_parent_id",
          "type": "integer",
          "primaryKey": false,
          "notNull": true
        },
        "_path": {
          "name": "_path",
          "type": "text",
          "primaryKey": false,
          "notNull": true
        },
        "id": {
          "name": "id",
          "type": "varchar",
          "primaryKey": true,
          "notNull": true
        },
        "title": {
          "name": "title",
          "type": "varchar",
          "primaryKey": false,
          "notNull": true
        },
        "image_id": {
          "name": "image_id",
          "type": "integer",
          "primaryKey": false,
          "notNull": true
        },
        "block_name": {
          "name": "block_name",
          "type": "varchar",
          "primaryKey": false,
          "notNull": false
        }
      },
      "indexes": {
        "pages_blocks_header_order_idx": {
          "name": "pages_blocks_header_order_idx",
          "columns": [
            {
              "expression": "_order",
              "isExpression": false,
              "asc": true,
              "nulls": "last"
            }
          ],
          "isUnique": false,
          "concurrently": false,
          "method": "btree",
          "with": {}
        },
        "pages_blocks_header_parent_id_idx": {
          "name": "pages_blocks_header_parent_id_idx",
          "columns": [
            {
              "expression": "_parent_id",
              "isExpression": false,
              "asc": true,
              "nulls": "last"
            }
          ],
          "isUnique": false,
          "concurrently": false,
          "method": "btree",
          "with": {}
        },
        "pages_blocks_header_path_idx": {
          "name": "pages_blocks_header_path_idx",
          "columns": [
            {
              "expression": "_path",
              "isExpression": false,
              "asc": true,
              "nulls": "last"
            }
          ],
          "isUnique": false,
          "concurrently": false,
          "method": "btree",
          "with": {}
        },
        "pages_blocks_header_image_idx": {
          "name": "pages_blocks_header_image_idx",
          "columns": [
            {
              "expression": "image_id",
              "isExpression": false,
              "asc": true,
              "nulls": "last"
            }
          ],
          "isUnique": false,
          "concurrently": false,
          "method": "btree",
          "with": {}
        }
      },
      "foreignKeys": {
        "pages_blocks_header_image_id_media_id_fk": {
          "name": "pages_blocks_header_image_id_media_id_fk",
          "tableFrom": "pages_blocks_header",
          "tableTo": "media",
          "columnsFrom": [
            "image_id"
          ],
          "columnsTo": [
            "id"
          ],
          "onDelete": "set null",
          "onUpdate": "no action"
        },
        "pages_blocks_header_parent_id_fk": {
          "name": "pages_blocks_header_parent_id_fk",
          "tableFrom": "pages_blocks_header",
          "tableTo": "pages",
          "columnsFrom": [
            "_parent_id"
          ],
          "columnsTo": [
            "id"
          ],
          "onDelete": "cascade",
          "onUpdate": "no action"
        }
      },
      "compositePrimaryKeys": {},
      "uniqueConstraints": {},
      "policies": {},
      "checkConstraints": {},
      "isRLSEnabled": false
    },
    "public.pages": {
      "name": "pages",
      "schema": "",
      "columns": {
        "id": {
          "name": "id",
          "type": "serial",
          "primaryKey": true,
          "notNull": true
        },
        "title": {
          "name": "title",
          "type": "varchar",
          "primaryKey": false,
          "notNull": true
        },
        "slug": {
          "name": "slug",
          "type": "varchar",
          "primaryKey": false,
          "notNull": false
        },
        "updated_at": {
          "name": "updated_at",
          "type": "timestamp(3) with time zone",
          "primaryKey": false,
          "notNull": true,
          "default": "now()"
        },
        "created_at": {
          "name": "created_at",
          "type": "timestamp(3) with time zone",
          "primaryKey": false,
          "notNull": true,
          "default": "now()"
        }
      },
      "indexes": {
        "pages_slug_idx": {
          "name": "pages_slug_idx",
          "columns": [
            {
              "expression": "slug",
              "isExpression": false,
              "asc": true,
              "nulls": "last"
            }
          ],
          "isUnique": true,
          "concurrently": false,
          "method": "btree",
          "with": {}
        },
        "pages_updated_at_idx": {
          "name": "pages_updated_at_idx",
          "columns": [
            {
              "expression": "updated_at",
              "isExpression": false,
              "asc": true,
              "nulls": "last"
            }
          ],
          "isUnique": false,
          "concurrently": false,
          "method": "btree",
          "with": {}
        },
        "pages_created_at_idx": {
          "name": "pages_created_at_idx",
          "columns": [
            {
              "expression": "created_at",
              "isExpression": false,
              "asc": true,
              "nulls": "last"
            }
          ],
          "isUnique": false,
          "concurrently": false,
          "method": "btree",
          "with": {}
        }
      },
      "foreignKeys": {},
      "compositePrimaryKeys": {},
      "uniqueConstraints": {},
      "policies": {},
      "checkConstraints": {},
      "isRLSEnabled": false
    },
    "public.menu_items_sub_items": {
      "name": "menu_items_sub_items",
      "schema": "",
      "columns": {
        "_order": {
          "name": "_order",
          "type": "integer",
          "primaryKey": false,
          "notNull": true
        },
        "_parent_id": {
          "name": "_parent_id",
          "type": "integer",
          "primaryKey": false,
          "notNull": true
        },
        "id": {
          "name": "id",
          "type": "varchar",
          "primaryKey": true,
          "notNull": true
        },
        "name": {
          "name": "name",
          "type": "varchar",
          "primaryKey": false,
          "notNull": true
        },
        "price": {
          "name": "price",
          "type": "numeric",
          "primaryKey": false,
          "notNull": true
        }
      },
      "indexes": {
        "menu_items_sub_items_order_idx": {
          "name": "menu_items_sub_items_order_idx",
          "columns": [
            {
              "expression": "_order",
              "isExpression": false,
              "asc": true,
              "nulls": "last"
            }
          ],
          "isUnique": false,
          "concurrently": false,
          "method": "btree",
          "with": {}
        },
        "menu_items_sub_items_parent_id_idx": {
          "name": "menu_items_sub_items_parent_id_idx",
          "columns": [
            {
              "expression": "_parent_id",
              "isExpression": false,
              "asc": true,
              "nulls": "last"
            }
          ],
          "isUnique": false,
          "concurrently": false,
          "method": "btree",
          "with": {}
        }
      },
      "foreignKeys": {
        "menu_items_sub_items_parent_id_fk": {
          "name": "menu_items_sub_items_parent_id_fk",
          "tableFrom": "menu_items_sub_items",
          "tableTo": "menu_items",
          "columnsFrom": [
            "_parent_id"
          ],
          "columnsTo": [
            "id"
          ],
          "onDelete": "cascade",
          "onUpdate": "no action"
        }
      },
      "compositePrimaryKeys": {},
      "uniqueConstraints": {},
      "policies": {},
      "checkConstraints": {},
      "isRLSEnabled": false
    },
    "public.menu_items": {
      "name": "menu_items",
      "schema": "",
      "columns": {
        "id": {
          "name": "id",
          "type": "serial",
          "primaryKey": true,
          "notNull": true
        },
        "order": {
          "name": "order",
          "type": "numeric",
          "primaryKey": false,
          "notNull": true
        },
        "name": {
          "name": "name",
          "type": "varchar",
          "primaryKey": false,
          "notNull": true
        },
        "description": {
          "name": "description",
          "type": "jsonb",
          "primaryKey": false,
          "notNull": false
        },
        "price": {
          "name": "price",
          "type": "numeric",
          "primaryKey": false,
          "notNull": false
        },
        "image_id": {
          "name": "image_id",
          "type": "integer",
          "primaryKey": false,
          "notNull": false
        },
        "category_id": {
          "name": "category_id",
          "type": "integer",
          "primaryKey": false,
          "notNull": true
        },
        "is_sold_out": {
          "name": "is_sold_out",
          "type": "boolean",
          "primaryKey": false,
          "notNull": false,
          "default": false
        },
        "is_published": {
          "name": "is_published",
          "type": "boolean",
          "primaryKey": false,
          "notNull": false,
          "default": true
        },
        "updated_at": {
          "name": "updated_at",
          "type": "timestamp(3) with time zone",
          "primaryKey": false,
          "notNull": true,
          "default": "now()"
        },
        "created_at": {
          "name": "created_at",
          "type": "timestamp(3) with time zone",
          "primaryKey": false,
          "notNull": true,
          "default": "now()"
        }
      },
      "indexes": {
        "menu_items_image_idx": {
          "name": "menu_items_image_idx",
          "columns": [
            {
              "expression": "image_id",
              "isExpression": false,
              "asc": true,
              "nulls": "last"
            }
          ],
          "isUnique": false,
          "concurrently": false,
          "method": "btree",
          "with": {}
        },
        "menu_items_category_idx": {
          "name": "menu_items_category_idx",
          "columns": [
            {
              "expression": "category_id",
              "isExpression": false,
              "asc": true,
              "nulls": "last"
            }
          ],
          "isUnique": false,
          "concurrently": false,
          "method": "btree",
          "with": {}
        },
        "menu_items_updated_at_idx": {
          "name": "menu_items_updated_at_idx",
          "columns": [
            {
              "expression": "updated_at",
              "isExpression": false,
              "asc": true,
              "nulls": "last"
            }
          ],
          "isUnique": false,
          "concurrently": false,
          "method": "btree",
          "with": {}
        },
        "menu_items_created_at_idx": {
          "name": "menu_items_created_at_idx",
          "columns": [
            {
              "expression": "created_at",
              "isExpression": false,
              "asc": true,
              "nulls": "last"
            }
          ],
          "isUnique": false,
          "concurrently": false,
          "method": "btree",
          "with": {}
        }
      },
      "foreignKeys": {
        "menu_items_image_id_media_id_fk": {
          "name": "menu_items_image_id_media_id_fk",
          "tableFrom": "menu_items",
          "tableTo": "media",
          "columnsFrom": [
            "image_id"
          ],
          "columnsTo": [
            "id"
          ],
          "onDelete": "set null",
          "onUpdate": "no action"
        },
        "menu_items_category_id_categories_id_fk": {
          "name": "menu_items_category_id_categories_id_fk",
          "tableFrom": "menu_items",
          "tableTo": "categories",
          "columnsFrom": [
            "category_id"
          ],
          "columnsTo": [
            "id"
          ],
          "onDelete": "set null",
          "onUpdate": "no action"
        }
      },
      "compositePrimaryKeys": {},
      "uniqueConstraints": {},
      "policies": {},
      "checkConstraints": {},
      "isRLSEnabled": false
    },
    "public.categories": {
      "name": "categories",
      "schema": "",
      "columns": {
        "id": {
          "name": "id",
          "type": "serial",
          "primaryKey": true,
          "notNull": true
        },
        "name": {
          "name": "name",
          "type": "varchar",
          "primaryKey": false,
          "notNull": true
        },
        "description": {
          "name": "description",
          "type": "varchar",
          "primaryKey": false,
          "notNull": false
        },
        "order": {
          "name": "order",
          "type": "numeric",
          "primaryKey": false,
          "notNull": true,
          "default": 0
        },
        "updated_at": {
          "name": "updated_at",
          "type": "timestamp(3) with time zone",
          "primaryKey": false,
          "notNull": true,
          "default": "now()"
        },
        "created_at": {
          "name": "created_at",
          "type": "timestamp(3) with time zone",
          "primaryKey": false,
          "notNull": true,
          "default": "now()"
        }
      },
      "indexes": {
        "categories_updated_at_idx": {
          "name": "categories_updated_at_idx",
          "columns": [
            {
              "expression": "updated_at",
              "isExpression": false,
              "asc": true,
              "nulls": "last"
            }
          ],
          "isUnique": false,
          "concurrently": false,
          "method": "btree",
          "with": {}
        },
        "categories_created_at_idx": {
          "name": "categories_created_at_idx",
          "columns": [
            {
              "expression": "created_at",
              "isExpression": false,
              "asc": true,
              "nulls": "last"
            }
          ],
          "isUnique": false,
          "concurrently": false,
          "method": "btree",
          "with": {}
        }
      },
      "foreignKeys": {},
      "compositePrimaryKeys": {},
      "uniqueConstraints": {},
      "policies": {},
      "checkConstraints": {},
      "isRLSEnabled": false
    },
    "public.events": {
      "name": "events",
      "schema": "",
      "columns": {
        "id": {
          "name": "id",
          "type": "serial",
          "primaryKey": true,
          "notNull": true
        },
        "title": {
          "name": "title",
          "type": "varchar",
          "primaryKey": false,
          "notNull": true
        },
        "date": {
          "name": "date",
          "type": "timestamp(3) with time zone",
          "primaryKey": false,
          "notNull": true
        },
        "description": {
          "name": "description",
          "type": "jsonb",
          "primaryKey": false,
          "notNull": false
        },
        "location": {
          "name": "location",
          "type": "varchar",
          "primaryKey": false,
          "notNull": false
        },
        "image_id": {
          "name": "image_id",
          "type": "integer",
          "primaryKey": false,
          "notNull": false
        },
        "updated_at": {
          "name": "updated_at",
          "type": "timestamp(3) with time zone",
          "primaryKey": false,
          "notNull": true,
          "default": "now()"
        },
        "created_at": {
          "name": "created_at",
          "type": "timestamp(3) with time zone",
          "primaryKey": false,
          "notNull": true,
          "default": "now()"
        }
      },
      "indexes": {
        "events_image_idx": {
          "name": "events_image_idx",
          "columns": [
            {
              "expression": "image_id",
              "isExpression": false,
              "asc": true,
              "nulls": "last"
            }
          ],
          "isUnique": false,
          "concurrently": false,
          "method": "btree",
          "with": {}
        },
        "events_updated_at_idx": {
          "name": "events_updated_at_idx",
          "columns": [
            {
              "expression": "updated_at",
              "isExpression": false,
              "asc": true,
              "nulls": "last"
            }
          ],
          "isUnique": false,
          "concurrently": false,
          "method": "btree",
          "with": {}
        },
        "events_created_at_idx": {
          "name": "events_created_at_idx",
          "columns": [
            {
              "expression": "created_at",
              "isExpression": false,
              "asc": true,
              "nulls": "last"
            }
          ],
          "isUnique": false,
          "concurrently": false,
          "method": "btree",
          "with": {}
        }
      },
      "foreignKeys": {
        "events_image_id_media_id_fk": {
          "name": "events_image_id_media_id_fk",
          "tableFrom": "events",
          "tableTo": "media",
          "columnsFrom": [
            "image_id"
          ],
          "columnsTo": [
            "id"
          ],
          "onDelete": "set null",
          "onUpdate": "no action"
        }
      },
      "compositePrimaryKeys": {},
      "uniqueConstraints": {},
      "policies": {},
      "checkConstraints": {},
      "isRLSEnabled": false
    },
    "public.catering_menu_sub_items": {
      "name": "catering_menu_sub_items",
      "schema": "",
      "columns": {
        "_order": {
          "name": "_order",
          "type": "integer",
          "primaryKey": false,
          "notNull": true
        },
        "_parent_id": {
          "name": "_parent_id",
          "type": "integer",
          "primaryKey": false,
          "notNull": true
        },
        "id": {
          "name": "id",
          "type": "varchar",
          "primaryKey": true,
          "notNull": true
        },
        "name": {
          "name": "name",
          "type": "varchar",
          "primaryKey": false,
          "notNull": true
        },
        "price": {
          "name": "price",
          "type": "numeric",
          "primaryKey": false,
          "notNull": true
        }
      },
      "indexes": {
        "catering_menu_sub_items_order_idx": {
          "name": "catering_menu_sub_items_order_idx",
          "columns": [
            {
              "expression": "_order",
              "isExpression": false,
              "asc": true,
              "nulls": "last"
            }
          ],
          "isUnique": false,
          "concurrently": false,
          "method": "btree",
          "with": {}
        },
        "catering_menu_sub_items_parent_id_idx": {
          "name": "catering_menu_sub_items_parent_id_idx",
          "columns": [
            {
              "expression": "_parent_id",
              "isExpression": false,
              "asc": true,
              "nulls": "last"
            }
          ],
          "isUnique": false,
          "concurrently": false,
          "method": "btree",
          "with": {}
        }
      },
      "foreignKeys": {
        "catering_menu_sub_items_parent_id_fk": {
          "name": "catering_menu_sub_items_parent_id_fk",
          "tableFrom": "catering_menu_sub_items",
          "tableTo": "catering_menu",
          "columnsFrom": [
            "_parent_id"
          ],
          "columnsTo": [
            "id"
          ],
          "onDelete": "cascade",
          "onUpdate": "no action"
        }
      },
      "compositePrimaryKeys": {},
      "uniqueConstraints": {},
      "policies": {},
      "checkConstraints": {},
      "isRLSEnabled": false
    },
    "public.catering_menu": {
      "name": "catering_menu",
      "schema": "",
      "columns": {
        "id": {
          "name": "id",
          "type": "serial",
          "primaryKey": true,
          "notNull": true
        },
        "order": {
          "name": "order",
          "type": "numeric",
          "primaryKey": false,
          "notNull": true
        },
        "name": {
          "name": "name",
          "type": "varchar",
          "primaryKey": false,
          "notNull": true
        },
        "description": {
          "name": "description",
          "type": "jsonb",
          "primaryKey": false,
          "notNull": false
        },
        "price": {
          "name": "price",
          "type": "numeric",
          "primaryKey": false,
          "notNull": false
        },
        "image_id": {
          "name": "image_id",
          "type": "integer",
          "primaryKey": false,
          "notNull": false
        },
        "category_id": {
          "name": "category_id",
          "type": "integer",
          "primaryKey": false,
          "notNull": true
        },
        "is_published": {
          "name": "is_published",
          "type": "boolean",
          "primaryKey": false,
          "notNull": false,
          "default": true
        },
        "minimum_order": {
          "name": "minimum_order",
          "type": "varchar",
          "primaryKey": false,
          "notNull": false
        },
        "updated_at": {
          "name": "updated_at",
          "type": "timestamp(3) with time zone",
          "primaryKey": false,
          "notNull": true,
          "default": "now()"
        },
        "created_at": {
          "name": "created_at",
          "type": "timestamp(3) with time zone",
          "primaryKey": false,
          "notNull": true,
          "default": "now()"
        }
      },
      "indexes": {
        "catering_menu_image_idx": {
          "name": "catering_menu_image_idx",
          "columns": [
            {
              "expression": "image_id",
              "isExpression": false,
              "asc": true,
              "nulls": "last"
            }
          ],
          "isUnique": false,
          "concurrently": false,
          "method": "btree",
          "with": {}
        },
        "catering_menu_category_idx": {
          "name": "catering_menu_category_idx",
          "columns": [
            {
              "expression": "category_id",
              "isExpression": false,
              "asc": true,
              "nulls": "last"
            }
          ],
          "isUnique": false,
          "concurrently": false,
          "method": "btree",
          "with": {}
        },
        "catering_menu_updated_at_idx": {
          "name": "catering_menu_updated_at_idx",
          "columns": [
            {
              "expression": "updated_at",
              "isExpression": false,
              "asc": true,
              "nulls": "last"
            }
          ],
          "isUnique": false,
          "concurrently": false,
          "method": "btree",
          "with": {}
        },
        "catering_menu_created_at_idx": {
          "name": "catering_menu_created_at_idx",
          "columns": [
            {
              "expression": "created_at",
              "isExpression": false,
              "asc": true,
              "nulls": "last"
            }
          ],
          "isUnique": false,
          "concurrently": false,
          "method": "btree",
          "with": {}
        }
      },
      "foreignKeys": {
        "catering_menu_image_id_media_id_fk": {
          "name": "catering_menu_image_id_media_id_fk",
          "tableFrom": "catering_menu",
          "tableTo": "media",
          "columnsFrom": [
            "image_id"
          ],
          "columnsTo": [
            "id"
          ],
          "onDelete": "set null",
          "onUpdate": "no action"
        },
        "catering_menu_category_id_catering_categories_id_fk": {
          "name": "catering_menu_category_id_catering_categories_id_fk",
          "tableFrom": "catering_menu",
          "tableTo": "catering_categories",
          "columnsFrom": [
            "category_id"
          ],
          "columnsTo": [
            "id"
          ],
          "onDelete": "set null",
          "onUpdate": "no action"
        }
      },
      "compositePrimaryKeys": {},
      "uniqueConstraints": {},
      "policies": {},
      "checkConstraints": {},
      "isRLSEnabled": false
    },
    "public.catering_categories": {
      "name": "catering_categories",
      "schema": "",
      "columns": {
        "id": {
          "name": "id",
          "type": "serial",
          "primaryKey": true,
          "notNull": true
        },
        "name": {
          "name": "name",
          "type": "varchar",
          "primaryKey": false,
          "notNull": true
        },
        "description": {
          "name": "description",
          "type": "varchar",
          "primaryKey": false,
          "notNull": false
        },
        "order": {
          "name": "order",
          "type": "numeric",
          "primaryKey": false,
          "notNull": true,
          "default": 0
        },
        "updated_at": {
          "name": "updated_at",
          "type": "timestamp(3) with time zone",
          "primaryKey": false,
          "notNull": true,
          "default": "now()"
        },
        "created_at": {
          "name": "created_at",
          "type": "timestamp(3) with time zone",
          "primaryKey": false,
          "notNull": true,
          "default": "now()"
        }
      },
      "indexes": {
        "catering_categories_updated_at_idx": {
          "name": "catering_categories_updated_at_idx",
          "columns": [
            {
              "expression": "updated_at",
              "isExpression": false,
              "asc": true,
              "nulls": "last"
            }
          ],
          "isUnique": false,
          "concurrently": false,
          "method": "btree",
          "with": {}
        },
        "catering_categories_created_at_idx": {
          "name": "catering_categories_created_at_idx",
          "columns": [
            {
              "expression": "created_at",
              "isExpression": false,
              "asc": true,
              "nulls": "last"
            }
          ],
          "isUnique": false,
          "concurrently": false,
          "method": "btree",
          "with": {}
        }
      },
      "foreignKeys": {},
      "compositePrimaryKeys": {},
      "uniqueConstraints": {},
      "policies": {},
      "checkConstraints": {},
      "isRLSEnabled": false
    },
    "public.payload_locked_documents": {
      "name": "payload_locked_documents",
      "schema": "",
      "columns": {
        "id": {
          "name": "id",
          "type": "serial",
          "primaryKey": true,
          "notNull": true
        },
        "global_slug": {
          "name": "global_slug",
          "type": "varchar",
          "primaryKey": false,
          "notNull": false
        },
        "updated_at": {
          "name": "updated_at",
          "type": "timestamp(3) with time zone",
          "primaryKey": false,
          "notNull": true,
          "default": "now()"
        },
        "created_at": {
          "name": "created_at",
          "type": "timestamp(3) with time zone",
          "primaryKey": false,
          "notNull": true,
          "default": "now()"
        }
      },
      "indexes": {
        "payload_locked_documents_global_slug_idx": {
          "name": "payload_locked_documents_global_slug_idx",
          "columns": [
            {
              "expression": "global_slug",
              "isExpression": false,
              "asc": true,
              "nulls": "last"
            }
          ],
          "isUnique": false,
          "concurrently": false,
          "method": "btree",
          "with": {}
        },
        "payload_locked_documents_updated_at_idx": {
          "name": "payload_locked_documents_updated_at_idx",
          "columns": [
            {
              "expression": "updated_at",
              "isExpression": false,
              "asc": true,
              "nulls": "last"
            }
          ],
          "isUnique": false,
          "concurrently": false,
          "method": "btree",
          "with": {}
        },
        "payload_locked_documents_created_at_idx": {
          "name": "payload_locked_documents_created_at_idx",
          "columns": [
            {
              "expression": "created_at",
              "isExpression": false,
              "asc": true,
              "nulls": "last"
            }
          ],
          "isUnique": false,
          "concurrently": false,
          "method": "btree",
          "with": {}
        }
      },
      "foreignKeys": {},
      "compositePrimaryKeys": {},
      "uniqueConstraints": {},
      "policies": {},
      "checkConstraints": {},
      "isRLSEnabled": false
    },
    "public.payload_locked_documents_rels": {
      "name": "payload_locked_documents_rels",
      "schema": "",
      "columns": {
        "id": {
          "name": "id",
          "type": "serial",
          "primaryKey": true,
          "notNull": true
        },
        "order": {
          "name": "order",
          "type": "integer",
          "primaryKey": false,
          "notNull": false
        },
        "parent_id": {
          "name": "parent_id",
          "type": "integer",
          "primaryKey": false,
          "notNull": true
        },
        "path": {
          "name": "path",
          "type": "varchar",
          "primaryKey": false,
          "notNull": true
        },
        "users_id": {
          "name": "users_id",
          "type": "integer",
          "primaryKey": false,
          "notNull": false
        },
        "media_id": {
          "name": "media_id",
          "type": "integer",
          "primaryKey": false,
          "notNull": false
        },
        "pages_id": {
          "name": "pages_id",
          "type": "integer",
          "primaryKey": false,
          "notNull": false
        },
        "menu_items_id": {
          "name": "menu_items_id",
          "type": "integer",
          "primaryKey": false,
          "notNull": false
        },
        "categories_id": {
          "name": "categories_id",
          "type": "integer",
          "primaryKey": false,
          "notNull": false
        },
        "events_id": {
          "name": "events_id",
          "type": "integer",
          "primaryKey": false,
          "notNull": false
        },
        "catering_menu_id": {
          "name": "catering_menu_id",
          "type": "integer",
          "primaryKey": false,
          "notNull": false
        },
        "catering_categories_id": {
          "name": "catering_categories_id",
          "type": "integer",
          "primaryKey": false,
          "notNull": false
        }
      },
      "indexes": {
        "payload_locked_documents_rels_order_idx": {
          "name": "payload_locked_documents_rels_order_idx",
          "columns": [
            {
              "expression": "order",
              "isExpression": false,
              "asc": true,
              "nulls": "last"
            }
          ],
          "isUnique": false,
          "concurrently": false,
          "method": "btree",
          "with": {}
        },
        "payload_locked_documents_rels_parent_idx": {
          "name": "payload_locked_documents_rels_parent_idx",
          "columns": [
            {
              "expression": "parent_id",
              "isExpression": false,
              "asc": true,
              "nulls": "last"
            }
          ],
          "isUnique": false,
          "concurrently": false,
          "method": "btree",
          "with": {}
        },
        "payload_locked_documents_rels_path_idx": {
          "name": "payload_locked_documents_rels_path_idx",
          "columns": [
            {
              "expression": "path",
              "isExpression": false,
              "asc": true,
              "nulls": "last"
            }
          ],
          "isUnique": false,
          "concurrently": false,
          "method": "btree",
          "with": {}
        },
        "payload_locked_documents_rels_users_id_idx": {
          "name": "payload_locked_documents_rels_users_id_idx",
          "columns": [
            {
              "expression": "users_id",
              "isExpression": false,
              "asc": true,
              "nulls": "last"
            }
          ],
          "isUnique": false,
          "concurrently": false,
          "method": "btree",
          "with": {}
        },
        "payload_locked_documents_rels_media_id_idx": {
          "name": "payload_locked_documents_rels_media_id_idx",
          "columns": [
            {
              "expression": "media_id",
              "isExpression": false,
              "asc": true,
              "nulls": "last"
            }
          ],
          "isUnique": false,
          "concurrently": false,
          "method": "btree",
          "with": {}
        },
        "payload_locked_documents_rels_pages_id_idx": {
          "name": "payload_locked_documents_rels_pages_id_idx",
          "columns": [
            {
              "expression": "pages_id",
              "isExpression": false,
              "asc": true,
              "nulls": "last"
            }
          ],
          "isUnique": false,
          "concurrently": false,
          "method": "btree",
          "with": {}
        },
        "payload_locked_documents_rels_menu_items_id_idx": {
          "name": "payload_locked_documents_rels_menu_items_id_idx",
          "columns": [
            {
              "expression": "menu_items_id",
              "isExpression": false,
              "asc": true,
              "nulls": "last"
            }
          ],
          "isUnique": false,
          "concurrently": false,
          "method": "btree",
          "with": {}
        },
        "payload_locked_documents_rels_categories_id_idx": {
          "name": "payload_locked_documents_rels_categories_id_idx",
          "columns": [
            {
              "expression": "categories_id",
              "isExpression": false,
              "asc": true,
              "nulls": "last"
            }
          ],
          "isUnique": false,
          "concurrently": false,
          "method": "btree",
          "with": {}
        },
        "payload_locked_documents_rels_events_id_idx": {
          "name": "payload_locked_documents_rels_events_id_idx",
          "columns": [
            {
              "expression": "events_id",
              "isExpression": false,
              "asc": true,
              "nulls": "last"
            }
          ],
          "isUnique": false,
          "concurrently": false,
          "method": "btree",
          "with": {}
        },
        "payload_locked_documents_rels_catering_menu_id_idx": {
          "name": "payload_locked_documents_rels_catering_menu_id_idx",
          "columns": [
            {
              "expression": "catering_menu_id",
              "isExpression": false,
              "asc": true,
              "nulls": "last"
            }
          ],
          "isUnique": false,
          "concurrently": false,
          "method": "btree",
          "with": {}
        },
        "payload_locked_documents_rels_catering_categories_id_idx": {
          "name": "payload_locked_documents_rels_catering_categories_id_idx",
          "columns": [
            {
              "expression": "catering_categories_id",
              "isExpression": false,
              "asc": true,
              "nulls": "last"
            }
          ],
          "isUnique": false,
          "concurrently": false,
          "method": "btree",
          "with": {}
        }
      },
      "foreignKeys": {
        "payload_locked_documents_rels_parent_fk": {
          "name": "payload_locked_documents_rels_parent_fk",
          "tableFrom": "payload_locked_documents_rels",
          "tableTo": "payload_locked_documents",
          "columnsFrom": [
            "parent_id"
          ],
          "columnsTo": [
            "id"
          ],
          "onDelete": "cascade",
          "onUpdate": "no action"
        },
        "payload_locked_documents_rels_users_fk": {
          "name": "payload_locked_documents_rels_users_fk",
          "tableFrom": "payload_locked_documents_rels",
          "tableTo": "users",
          "columnsFrom": [
            "users_id"
          ],
          "columnsTo": [
            "id"
          ],
          "onDelete": "cascade",
          "onUpdate": "no action"
        },
        "payload_locked_documents_rels_media_fk": {
          "name": "payload_locked_documents_rels_media_fk",
          "tableFrom": "payload_locked_documents_rels",
          "tableTo": "media",
          "columnsFrom": [
            "media_id"
          ],
          "columnsTo": [
            "id"
          ],
          "onDelete": "cascade",
          "onUpdate": "no action"
        },
        "payload_locked_documents_rels_pages_fk": {
          "name": "payload_locked_documents_rels_pages_fk",
          "tableFrom": "payload_locked_documents_rels",
          "tableTo": "pages",
          "columnsFrom": [
            "pages_id"
          ],
          "columnsTo": [
            "id"
          ],
          "onDelete": "cascade",
          "onUpdate": "no action"
        },
        "payload_locked_documents_rels_menu_items_fk": {
          "name": "payload_locked_documents_rels_menu_items_fk",
          "tableFrom": "payload_locked_documents_rels",
          "tableTo": "menu_items",
          "columnsFrom": [
            "menu_items_id"
          ],
          "columnsTo": [
            "id"
          ],
          "onDelete": "cascade",
          "onUpdate": "no action"
        },
        "payload_locked_documents_rels_categories_fk": {
          "name": "payload_locked_documents_rels_categories_fk",
          "tableFrom": "payload_locked_documents_rels",
          "tableTo": "categories",
          "columnsFrom": [
            "categories_id"
          ],
          "columnsTo": [
            "id"
          ],
          "onDelete": "cascade",
          "onUpdate": "no action"
        },
        "payload_locked_documents_rels_events_fk": {
          "name": "payload_locked_documents_rels_events_fk",
          "tableFrom": "payload_locked_documents_rels",
          "tableTo": "events",
          "columnsFrom": [
            "events_id"
          ],
          "columnsTo": [
            "id"
          ],
          "onDelete": "cascade",
          "onUpdate": "no action"
        },
        "payload_locked_documents_rels_catering_menu_fk": {
          "name": "payload_locked_documents_rels_catering_menu_fk",
          "tableFrom": "payload_locked_documents_rels",
          "tableTo": "catering_menu",
          "columnsFrom": [
            "catering_menu_id"
          ],
          "columnsTo": [
            "id"
          ],
          "onDelete": "cascade",
          "onUpdate": "no action"
        },
        "payload_locked_documents_rels_catering_categories_fk": {
          "name": "payload_locked_documents_rels_catering_categories_fk",
          "tableFrom": "payload_locked_documents_rels",
          "tableTo": "catering_categories",
          "columnsFrom": [
            "catering_categories_id"
          ],
          "columnsTo": [
            "id"
          ],
          "onDelete": "cascade",
          "onUpdate": "no action"
        }
      },
      "compositePrimaryKeys": {},
      "uniqueConstraints": {},
      "policies": {},
      "checkConstraints": {},
      "isRLSEnabled": false
    },
    "public.payload_preferences": {
      "name": "payload_preferences",
      "schema": "",
      "columns": {
        "id": {
          "name": "id",
          "type": "serial",
          "primaryKey": true,
          "notNull": true
        },
        "key": {
          "name": "key",
          "type": "varchar",
          "primaryKey": false,
          "notNull": false
        },
        "value": {
          "name": "value",
          "type": "jsonb",
          "primaryKey": false,
          "notNull": false
        },
        "updated_at": {
          "name": "updated_at",
          "type": "timestamp(3) with time zone",
          "primaryKey": false,
          "notNull": true,
          "default": "now()"
        },
        "created_at": {
          "name": "created_at",
          "type": "timestamp(3) with time zone",
          "primaryKey": false,
          "notNull": true,
          "default": "now()"
        }
      },
      "indexes": {
        "payload_preferences_key_idx": {
          "name": "payload_preferences_key_idx",
          "columns": [
            {
              "expression": "key",
              "isExpression": false,
              "asc": true,
              "nulls": "last"
            }
          ],
          "isUnique": false,
          "concurrently": false,
          "method": "btree",
          "with": {}
        },
        "payload_preferences_updated_at_idx": {
          "name": "payload_preferences_updated_at_idx",
          "columns": [
            {
              "expression": "updated_at",
              "isExpression": false,
              "asc": true,
              "nulls": "last"
            }
          ],
          "isUnique": false,
          "concurrently": false,
          "method": "btree",
          "with": {}
        },
        "payload_preferences_created_at_idx": {
          "name": "payload_preferences_created_at_idx",
          "columns": [
            {
              "expression": "created_at",
              "isExpression": false,
              "asc": true,
              "nulls": "last"
            }
          ],
          "isUnique": false,
          "concurrently": false,
          "method": "btree",
          "with": {}
        }
      },
      "foreignKeys": {},
      "compositePrimaryKeys": {},
      "uniqueConstraints": {},
      "policies": {},
      "checkConstraints": {},
      "isRLSEnabled": false
    },
    "public.payload_preferences_rels": {
      "name": "payload_preferences_rels",
      "schema": "",
      "columns": {
        "id": {
          "name": "id",
          "type": "serial",
          "primaryKey": true,
          "notNull": true
        },
        "order": {
          "name": "order",
          "type": "integer",
          "primaryKey": false,
          "notNull": false
        },
        "parent_id": {
          "name": "parent_id",
          "type": "integer",
          "primaryKey": false,
          "notNull": true
        },
        "path": {
          "name": "path",
          "type": "varchar",
          "primaryKey": false,
          "notNull": true
        },
        "users_id": {
          "name": "users_id",
          "type": "integer",
          "primaryKey": false,
          "notNull": false
        }
      },
      "indexes": {
        "payload_preferences_rels_order_idx": {
          "name": "payload_preferences_rels_order_idx",
          "columns": [
            {
              "expression": "order",
              "isExpression": false,
              "asc": true,
              "nulls": "last"
            }
          ],
          "isUnique": false,
          "concurrently": false,
          "method": "btree",
          "with": {}
        },
        "payload_preferences_rels_parent_idx": {
          "name": "payload_preferences_rels_parent_idx",
          "columns": [
            {
              "expression": "parent_id",
              "isExpression": false,
              "asc": true,
              "nulls": "last"
            }
          ],
          "isUnique": false,
          "concurrently": false,
          "method": "btree",
          "with": {}
        },
        "payload_preferences_rels_path_idx": {
          "name": "payload_preferences_rels_path_idx",
          "columns": [
            {
              "expression": "path",
              "isExpression": false,
              "asc": true,
              "nulls": "last"
            }
          ],
          "isUnique": false,
          "concurrently": false,
          "method": "btree",
          "with": {}
        },
        "payload_preferences_rels_users_id_idx": {
          "name": "payload_preferences_rels_users_id_idx",
          "columns": [
            {
              "expression": "users_id",
              "isExpression": false,
              "asc": true,
              "nulls": "last"
            }
          ],
          "isUnique": false,
          "concurrently": false,
          "method": "btree",
          "with": {}
        }
      },
      "foreignKeys": {
        "payload_preferences_rels_parent_fk": {
          "name": "payload_preferences_rels_parent_fk",
          "tableFrom": "payload_preferences_rels",
          "tableTo": "payload_preferences",
          "columnsFrom": [
            "parent_id"
          ],
          "columnsTo": [
            "id"
          ],
          "onDelete": "cascade",
          "onUpdate": "no action"
        },
        "payload_preferences_rels_users_fk": {
          "name": "payload_preferences_rels_users_fk",
          "tableFrom": "payload_preferences_rels",
          "tableTo": "users",
          "columnsFrom": [
            "users_id"
          ],
          "columnsTo": [
            "id"
          ],
          "onDelete": "cascade",
          "onUpdate": "no action"
        }
      },
      "compositePrimaryKeys": {},
      "uniqueConstraints": {},
      "policies": {},
      "checkConstraints": {},
      "isRLSEnabled": false
    },
    "public.payload_migrations": {
      "name": "payload_migrations",
      "schema": "",
      "columns": {
        "id": {
          "name": "id",
          "type": "serial",
          "primaryKey": true,
          "notNull": true
        },
        "name": {
          "name": "name",
          "type": "varchar",
          "primaryKey": false,
          "notNull": false
        },
        "batch": {
          "name": "batch",
          "type": "numeric",
          "primaryKey": false,
          "notNull": false
        },
        "updated_at": {
          "name": "updated_at",
          "type": "timestamp(3) with time zone",
          "primaryKey": false,
          "notNull": true,
          "default": "now()"
        },
        "created_at": {
          "name": "created_at",
          "type": "timestamp(3) with time zone",
          "primaryKey": false,
          "notNull": true,
          "default": "now()"
        }
      },
      "indexes": {
        "payload_migrations_updated_at_idx": {
          "name": "payload_migrations_updated_at_idx",
          "columns": [
            {
              "expression": "updated_at",
              "isExpression": false,
              "asc": true,
              "nulls": "last"
            }
          ],
          "isUnique": false,
          "concurrently": false,
          "method": "btree",
          "with": {}
        },
        "payload_migrations_created_at_idx": {
          "name": "payload_migrations_created_at_idx",
          "columns": [
            {
              "expression": "created_at",
              "isExpression": false,
              "asc": true,
              "nulls": "last"
            }
          ],
          "isUnique": false,
          "concurrently": false,
          "method": "btree",
          "with": {}
        }
      },
      "foreignKeys": {},
      "compositePrimaryKeys": {},
      "uniqueConstraints": {},
      "policies": {},
      "checkConstraints": {},
      "isRLSEnabled": false
    },
    "public.social_media_links": {
      "name": "social_media_links",
      "schema": "",
      "columns": {
        "_order": {
          "name": "_order",
          "type": "integer",
          "primaryKey": false,
          "notNull": true
        },
        "_parent_id": {
          "name": "_parent_id",
          "type": "integer",
          "primaryKey": false,
          "notNull": true
        },
        "id": {
          "name": "id",
          "type": "varchar",
          "primaryKey": true,
          "notNull": true
        },
        "platform": {
          "name": "platform",
          "type": "varchar",
          "primaryKey": false,
          "notNull": true
        },
        "url": {
          "name": "url",
          "type": "varchar",
          "primaryKey": false,
          "notNull": true
        }
      },
      "indexes": {
        "social_media_links_order_idx": {
          "name": "social_media_links_order_idx",
          "columns": [
            {
              "expression": "_order",
              "isExpression": false,
              "asc": true,
              "nulls": "last"
            }
          ],
          "isUnique": false,
          "concurrently": false,
          "method": "btree",
          "with": {}
        },
        "social_media_links_parent_id_idx": {
          "name": "social_media_links_parent_id_idx",
          "columns": [
            {
              "expression": "_parent_id",
              "isExpression": false,
              "asc": true,
              "nulls": "last"
            }
          ],
          "isUnique": false,
          "concurrently": false,
          "method": "btree",
          "with": {}
        }
      },
      "foreignKeys": {
        "social_media_links_parent_id_fk": {
          "name": "social_media_links_parent_id_fk",
          "tableFrom": "social_media_links",
          "tableTo": "social_media",
          "columnsFrom": [
            "_parent_id"
          ],
          "columnsTo": [
            "id"
          ],
          "onDelete": "cascade",
          "onUpdate": "no action"
        }
      },
      "compositePrimaryKeys": {},
      "uniqueConstraints": {},
      "policies": {},
      "checkConstraints": {},
      "isRLSEnabled": false
    },
    "public.social_media": {
      "name": "social_media",
      "schema": "",
      "columns": {
        "id": {
          "name": "id",
          "type": "serial",
          "primaryKey": true,
          "notNull": true
        },
        "updated_at": {
          "name": "updated_at",
          "type": "timestamp(3) with time zone",
          "primaryKey": false,
          "notNull": false
        },
        "created_at": {
          "name": "created_at",
          "type": "timestamp(3) with time zone",
          "primaryKey": false,
          "notNull": false
        }
      },
      "indexes": {},
      "foreignKeys": {},
      "compositePrimaryKeys": {},
      "uniqueConstraints": {},
      "policies": {},
      "checkConstraints": {},
      "isRLSEnabled": false
    },
    "public.business_hours_schedule": {
      "name": "business_hours_schedule",
      "schema": "",
      "columns": {
        "_order": {
          "name": "_order",
          "type": "integer",
          "primaryKey": false,
          "notNull": true
        },
        "_parent_id": {
          "name": "_parent_id",
          "type": "integer",
          "primaryKey": false,
          "notNull": true
        },
        "id": {
          "name": "id",
          "type": "varchar",
          "primaryKey": true,
          "notNull": true
        },
        "day": {
          "name": "day",
          "type": "enum_business_hours_schedule_day",
          "typeSchema": "public",
          "primaryKey": false,
          "notNull": true
        },
        "time_range": {
          "name": "time_range",
          "type": "varchar",
          "primaryKey": false,
          "notNull": true
        }
      },
      "indexes": {
        "business_hours_schedule_order_idx": {
          "name": "business_hours_schedule_order_idx",
          "columns": [
            {
              "expression": "_order",
              "isExpression": false,
              "asc": true,
              "nulls": "last"
            }
          ],
          "isUnique": false,
          "concurrently": false,
          "method": "btree",
          "with": {}
        },
        "business_hours_schedule_parent_id_idx": {
          "name": "business_hours_schedule_parent_id_idx",
          "columns": [
            {
              "expression": "_parent_id",
              "isExpression": false,
              "asc": true,
              "nulls": "last"
            }
          ],
          "isUnique": false,
          "concurrently": false,
          "method": "btree",
          "with": {}
        }
      },
      "foreignKeys": {
        "business_hours_schedule_parent_id_fk": {
          "name": "business_hours_schedule_parent_id_fk",
          "tableFrom": "business_hours_schedule",
          "tableTo": "business_hours",
          "columnsFrom": [
            "_parent_id"
          ],
          "columnsTo": [
            "id"
          ],
          "onDelete": "cascade",
          "onUpdate": "no action"
        }
      },
      "compositePrimaryKeys": {},
      "uniqueConstraints": {},
      "policies": {},
      "checkConstraints": {},
      "isRLSEnabled": false
    },
    "public.business_hours": {
      "name": "business_hours",
      "schema": "",
      "columns": {
        "id": {
          "name": "id",
          "type": "serial",
          "primaryKey": true,
          "notNull": true
        },
        "updated_at": {
          "name": "updated_at",
          "type": "timestamp(3) with time zone",
          "primaryKey": false,
          "notNull": false
        },
        "created_at": {
          "name": "created_at",
          "type": "timestamp(3) with time zone",
          "primaryKey": false,
          "notNull": false
        }
      },
      "indexes": {},
      "foreignKeys": {},
      "compositePrimaryKeys": {},
      "uniqueConstraints": {},
      "policies": {},
      "checkConstraints": {},
      "isRLSEnabled": false
    },
    "public.status": {
      "name": "status",
      "schema": "",
      "columns": {
        "id": {
          "name": "id",
          "type": "serial",
          "primaryKey": true,
          "notNull": true
        },
        "current_status": {
          "name": "current_status",
          "type": "enum_status_current_status",
          "typeSchema": "public",
          "primaryKey": false,
          "notNull": true,
          "default": "'open'"
        },
        "updated_at": {
          "name": "updated_at",
          "type": "timestamp(3) with time zone",
          "primaryKey": false,
          "notNull": false
        },
        "created_at": {
          "name": "created_at",
          "type": "timestamp(3) with time zone",
          "primaryKey": false,
          "notNull": false
        }
      },
      "indexes": {},
      "foreignKeys": {},
      "compositePrimaryKeys": {},
      "uniqueConstraints": {},
      "policies": {},
      "checkConstraints": {},
      "isRLSEnabled": false
    },
    "public.contact_info": {
      "name": "contact_info",
      "schema": "",
      "columns": {
        "id": {
          "name": "id",
          "type": "serial",
          "primaryKey": true,
          "notNull": true
        },
        "email": {
          "name": "email",
          "type": "varchar",
          "primaryKey": false,
          "notNull": false
        },
        "phone": {
          "name": "phone",
          "type": "varchar",
          "primaryKey": false,
          "notNull": false
        },
        "address_street": {
          "name": "address_street",
          "type": "varchar",
          "primaryKey": false,
          "notNull": false
        },
        "address_city": {
          "name": "address_city",
          "type": "varchar",
          "primaryKey": false,
          "notNull": false
        },
        "address_state": {
          "name": "address_state",
          "type": "varchar",
          "primaryKey": false,
          "notNull": false
        },
        "address_zip_code": {
          "name": "address_zip_code",
          "type": "varchar",
          "primaryKey": false,
          "notNull": false
        },
        "updated_at": {
          "name": "updated_at",
          "type": "timestamp(3) with time zone",
          "primaryKey": false,
          "notNull": false
        },
        "created_at": {
          "name": "created_at",
          "type": "timestamp(3) with time zone",
          "primaryKey": false,
          "notNull": false
        }
      },
      "indexes": {},
      "foreignKeys": {},
      "compositePrimaryKeys": {},
      "uniqueConstraints": {},
      "policies": {},
      "checkConstraints": {},
      "isRLSEnabled": false
    }
  },
  "enums": {
    "public.enum_pages_blocks_hero_ctas_icon": {
      "name": "enum_pages_blocks_hero_ctas_icon",
      "schema": "public",
      "values": [
        "",
        "Utensils",
        "MapPin"
      ]
    },
    "public.enum_pages_blocks_hero_image_position": {
      "name": "enum_pages_blocks_hero_image_position",
      "schema": "public",
      "values": [
        "left",
        "right"
      ]
    },
    "public.enum_business_hours_schedule_day": {
      "name": "enum_business_hours_schedule_day",
      "schema": "public",
      "values": [
        "monday",
        "tuesday",
        "wednesday",
        "thursday",
        "friday",
        "saturday",
        "sunday"
      ]
    },
    "public.enum_status_current_status": {
      "name": "enum_status_current_status",
      "schema": "public",
      "values": [
        "open",
        "sold-out",
        "closed-unscheduled"
      ]
    }
  },
  "schemas": {},
  "sequences": {},
  "roles": {},
  "policies": {},
  "views": {},
  "_meta": {
    "schemas": {},
    "tables": {},
    "columns": {}
  }
}